__version__.py
cli/__init__.py
cli/blog.py
cli/config.py
cli/prompt.py
cli/utils.py
core/__init__.py
core/blog.py
core/models/__init__.py
core/models/item.py
core/models/service.py
core/repository/__init__.py
core/repository/common.py
core/repository/directory_dao.py
core/repository/file_dao.py
core/repository/items.py
core/repository/repository.py
core/utils/__init__.py
core/utils/asserts.py
core/utils/serialize.py
settings/__init__.py
settings/models.py
settings/utils.py
jekyll_cli-2.0.0.dist-info/METADATA
jekyll_cli-2.0.0.dist-info/WHEEL
jekyll_cli-2.0.0.dist-info/entry_points.txt
jekyll_cli-2.0.0.dist-info/licenses/LICENSE
jekyll_cli-2.0.0.dist-info/RECORD
