Metadata-Version: 2.4
Name: jekyll-cli
Version: 2.0.0
Summary: Jekyll Blog CLI Tool
Author-email: John Wei <wzy1048168235@163.com>
License-Expression: MIT
License-File: LICENSE
Requires-Python: >=3.12
Requires-Dist: inquirerpy>=0.3.4
Requires-Dist: pydantic>=2.11.5
Requires-Dist: ruamel-yaml-string>=0.1.1
Requires-Dist: tomlkit>=0.13.3
Requires-Dist: typer>=0.12.5
